chromie/__init__.py
chromie/__version__.py
chromie/auth.py
chromie/chromie.py
chromie/config.py
chromie/enum.py
chromie/main.py
chromie/parser.py
chromie/utils.py
chromie/webstore.py
chromie/commands/__init__.py
chromie/commands/config.py
chromie/commands/deploy.py
chromie/commands/init.py
chromie/commands/package.py
chromie/commands/preview.py
chromie/commands/publish.py
chromie/commands/update.py
chromie/commands/upload.py
tests/__init__.py
tests/test_config.py
tests/test_init.py
tests/test_main.py
tests/test_package.py
tests/test_parser.py
tests/test_this.py
tests/utils.py
chromie-0.3.3.dist-info/LICENSE
chromie-0.3.3.dist-info/METADATA
chromie-0.3.3.dist-info/WHEEL
chromie-0.3.3.dist-info/entry_points.txt
chromie-0.3.3.dist-info/top_level.txt
chromie-0.3.3.dist-info/RECORD
