Metadata-Version: 2.1
Name: chromie
Version: 0.3.3
Summary: A simple utility CLI tool for packaging and maintaining chrome extensions.
Home-page: https://github.com/Sandersland/chromie
Author: Steffen Andersland
Author-email: steffen@andersland.dev
License: MIT
Platform: UNKNOWN
Requires-Python: >=3
Requires-Dist: requests (<3,>=2.24.0)
Requires-Dist: cryptography (<4,>=3.0)
Requires-Dist: PyJWT (<2,>=1.7.1)
Provides-Extra: dev
Requires-Dist: twine ; extra == 'dev'
Requires-Dist: black ; extra == 'dev'
